{
  "DotNetProjectDirectory": "./Dntc.Samples.Octahedron.Common",
  "BuildInDebugMode": true,
  "AssemblyDirectory": "./Dntc.Samples.Octahedron.Common/bin/Debug/net8.0",
  "AssembliesToLoad": [
    "Dntc.Samples.Octahedron.Common.dll"
  ],
  "MethodsToTranspile": [
    "Dntc.Samples.Octahedron.Common.Camera Dntc.Samples.Octahedron.Common.Camera::Default()",
    "System.Void Dntc.Samples.Octahedron.Common.Renderer::Render(System.UInt16[],Dntc.Samples.Octahedron.Common.Camera,System.Single)"
  ],
  "OutputDirectory": "./Octahedron.Sdl/generated"
}
